stefan_dataframe_utils/__init__.py
stefan_dataframe_utils/df_cache.py
stefan_dataframe_utils/df_optimize.py
stefan_dataframe_utils/logger.py
stefan_dataframe_utils-0.1.0.dist-info/WHEEL
stefan_dataframe_utils-0.1.0.dist-info/METADATA
stefan_dataframe_utils-0.1.0.dist-info/RECORD
