Metadata-Version: 2.1
Name: stefan-dataframe-utils
Version: 0.1.0
Summary: 
Author: Stefan Bader
Author-email: baderstefan@gmx.de
Requires-Python: >=3.6.2,<3.7.0
Classifier: Programming Language :: Python :: 3
Classifier: Programming Language :: Python :: 3.6
Requires-Dist: pandas (==1.1.5)
Requires-Dist: pyarrow (==6.0.1)
Requires-Dist: python-json-logger (>=2.0.2,<3.0.0)
